{
    "_class" : "hudson.model.FreeStyleProject",
    "allBuilds" : [
        {
            "_class" : "hudson.model.FreeStyleBuild",
            "duration" : 0,
            "fullDisplayName" : "Call of Modern Shooter #2838",
            "id" : "2838",
            "number" : 2838,
            "result" : "FAILURE",
            "builtOn" : "Build1",
            "timestamp" : 1594199576341
        },           
        {
            "_class" : "hudson.model.FreeStyleBuild",
            "duration" : 0,
            "fullDisplayName" : "Call of Modern Shooter #2837",
            "id" : "2837",
            "number" : 2837,
            "result" : "FAILURE",
            "builtOn" : "Build1",
            "timestamp" : 1594199566341
        },             
        {
            "_class" : "hudson.model.FreeStyleBuild",
            "duration" : 0,
            "fullDisplayName" : "Call of Modern Shooter #2836",
            "id" : "2836",
            "number" : 2836,
            "result" : "FAILURE",
            "builtOn" : "Build1",
            "timestamp" : 1594199556341
        },         
        {
            "_class" : "hudson.model.FreeStyleBuild",
            "duration" : 0,
            "fullDisplayName" : "Call of Modern Shooter #2835",
            "id" : "2835",
            "number" : 2835,
            "result" : "FAILURE",
            "builtOn" : "Build1",
            "timestamp" : 1594199546351
        },        
        {
            "_class" : "hudson.model.FreeStyleBuild",
            "duration" : 0,
            "fullDisplayName" : "Call of Modern Shooter #2834",
            "id" : "2834",
            "number" : 2834,
            "result" : "FAILURE",
            "builtOn" : "Build1",
            "timestamp" : 1594199546340
        },
        {
            "_class" : "hudson.model.FreeStyleBuild",
            "duration" : 0,
            "fullDisplayName" : "Call of Modern Shooter #2833",
            "id" : "2833",
            "number" : 2833,
            "result" : "FAILURE",
            "builtOn" : "Build2",
            "timestamp" : 1594197546340
        },
        {
            "_class" : "hudson.model.FreeStyleBuild",
            "duration" : 2294032,
            "fullDisplayName" : "Call of Modern Shooter #2832",
            "id" : "2832",
            "number" : 2832,
            "result" : "SUCCESS",
            "builtOn" : "Build1",
            "timestamp" : 1594194864358
        },
        {
            "_class" : "hudson.model.FreeStyleBuild",
            "duration" : 2298225,
            "fullDisplayName" : "Call of Modern Shooter #2831",
            "id" : "2831",
            "number" : 2831,
            "result" : "SUCCESS",
            "builtOn" : "Build2",
            "timestamp" : 1594192566047
        }
    ]
}